imap_auth_provider.py
matrix_synapse_imap-0.0.5.dist-info/LICENSE
matrix_synapse_imap-0.0.5.dist-info/METADATA
matrix_synapse_imap-0.0.5.dist-info/WHEEL
matrix_synapse_imap-0.0.5.dist-info/top_level.txt
matrix_synapse_imap-0.0.5.dist-info/RECORD
